twosample/__init__.py
twosample/twosample.py
two_sample_binomial-0.0.4.dist-info/LICENSE
two_sample_binomial-0.0.4.dist-info/METADATA
two_sample_binomial-0.0.4.dist-info/WHEEL
two_sample_binomial-0.0.4.dist-info/top_level.txt
two_sample_binomial-0.0.4.dist-info/RECORD
