Metadata-Version: 2.1
Name: two-sample-binomial
Version: 0.0.4
Summary: Several two-samples tests for count data
Home-page: https://github.com/alonkipnis/higher-criticism-test
Download-URL: https://github.com/alonkipnis/higher-criticism-test
Author: Alon Kipnis
Author-email: alonkipnis@gmail.com
Classifier: Programming Language :: Python :: 3
Classifier: License :: OSI Approved :: MIT License
Classifier: Operating System :: OS Independent
Requires-Python: >=3.6
License-File: LICENSE
Requires-Dist: numpy >=1.6
Requires-Dist: scipy[stats]
